djadmin_filters/__init__.py
djadmin_filters/apps.py
djadmin_filters/default_app_config.py
djadmin_filters/djadmin_hooks.py
djadmin_filters/filterset_factory.py
djadmin_filters/mixins.py
djadmin_filters/static/djadmin/djadmin_filters/css/djadmin_filters.css
djadmin_filters/static/djadmin/djadmin_filters/js/djadmin_filters.js
djadmin_filters/templates/djadmin/djadmin_filters/filter_widget.html
djadmin_filters-0.1.2.dist-info/licenses/LICENSE
djadmin_filters-0.1.2.dist-info/METADATA
djadmin_filters-0.1.2.dist-info/WHEEL
djadmin_filters-0.1.2.dist-info/entry_points.txt
djadmin_filters-0.1.2.dist-info/top_level.txt
djadmin_filters-0.1.2.dist-info/RECORD
