Metadata-Version: 2.4
Name: djadmin-filters
Version: 0.1.2
Summary: Django-filter integration for django-admin-deux
Author-email: Emma Delescolle <dev@levit.be>
License: MIT
Project-URL: Repository, https://codeberg.org/emmaDelescolle/django-admin-deux/src/branch/main/djadmin-filters
Project-URL: Documentation, https://django-admin-deux.readthedocs.io/en/latest/plugins/djadmin-filters/configuration/
Project-URL: Homepage, https://django-admin-deux.readthedocs.io/en/latest/plugins/djadmin-filters/configuration/
Classifier: Development Status :: 3 - Alpha
Classifier: Framework :: Django
Classifier: Framework :: Django :: 5.2
Classifier: Framework :: Django :: 6.0
Classifier: Programming Language :: Python :: 3.11
Classifier: Programming Language :: Python :: 3.12
Classifier: Programming Language :: Python :: 3.13
Classifier: Programming Language :: Python :: 3.14
Requires-Python: >=3.11
License-File: LICENSE
Requires-Dist: django-admin-deux>=0.1.0
Requires-Dist: django-filter>=23.0
Requires-Dist: Django>=5.2
Provides-Extra: dev
Requires-Dist: pytest>=7.4; extra == "dev"
Requires-Dist: pytest-django>=4.5; extra == "dev"
Requires-Dist: pytest-cov>=4.1; extra == "dev"
Requires-Dist: pytest-factoryboy>=2.6; extra == "dev"
Requires-Dist: factory-boy>=3.3; extra == "dev"
Requires-Dist: ruff>=0.8.0; extra == "dev"
Dynamic: license-file
